P_CombiningPValuesFinal/.DS_Store
P_CombiningPValuesFinal/__init__.py
P_CombiningPValuesFinal-0.1.4.dist-info/WHEEL
P_CombiningPValuesFinal-0.1.4.dist-info/METADATA
P_CombiningPValuesFinal-0.1.4.dist-info/RECORD
