Metadata-Version: 2.1
Name: P_CombiningPValuesFinal
Version: 0.1.4
Summary: Functions within this module allow for the use of multiple test statistics
Home-page: https://github.com/StatsGirl/Master2021
Author: Breya McGlown
Author-email: bswlker2@memphis.edu
Classifier: License :: OSI Approved :: MIT License
